LICENSE
MANIFEST.in
apicaller.py
setup.py
apicaller.egg-info/PKG-INFO
apicaller.egg-info/SOURCES.txt
apicaller.egg-info/dependency_links.txt
apicaller.egg-info/requires.txt
apicaller.egg-info/top_level.txt