Metadata-Version: 1.1
Name: apicaller
Version: 0.0.2a
Summary: APICaller makes the creating API client library easier.
Home-page: https://github.com/cespivo/apicaller
Author: Jan Češpivo
Author-email: jan.cespivo@gmail.com
License: Apache 2.0
Platform: UNKNOWN
Classifier: Development Status :: 3 - Alpha
Classifier: Environment :: Web Environment
Classifier: Intended Audience :: Developers
Classifier: License :: OSI Approved :: Apache Software License
Classifier: Operating System :: OS Independent
Classifier: Programming Language :: Python
Classifier: Topic :: Internet :: WWW/HTTP
